Metadata-Version: 2.1
Name: backwork-notifier-http
Version: 0.1.4
Summary: Backwork plug-in for HTTP notifications.
Home-page: https://github.com/IBM/backwork-notifier-http
Author: Ben Honda
Author-email: benhonda@ibm.com
License: Apache 2
Platform: UNKNOWN
Classifier: Development Status :: 3 - Alpha
Classifier: Environment :: Console
Classifier: Intended Audience :: Developers
Classifier: Intended Audience :: System Administrators
Classifier: Operating System :: POSIX :: Linux
Classifier: Programming Language :: Python :: 3.8
Classifier: License :: OSI Approved :: Apache Software License
Classifier: Topic :: Database
Classifier: Topic :: System :: Archiving :: Backup
Classifier: Topic :: Utilities
Requires-Dist: backwork
Requires-Dist: requests (==2.25.1)
